ribeye/aio/__init__.py
ribeye/aio/client.py
ribeye/aio/endpoint.py
ribeye/aio/internal/__init__.py
ribeye/aio/internal/adapter.py
ribeye/aio/internal/endpoint_descriptor.py
ribeye/aio/internal/pydantic_v1.py
ribeye/aio/internal/pydantic_v2.py
ribeye/aio/internal/request_template.py
ribeye/aio/option/__init__.py
ribeye/aio/option/cache.py
ribeye/aio/option/private.py
ribeye/aio/option/retry.py
ribeye/aio/option/throttle.py
ribeye/aio/response.py
ribeye/aio/types.py
ribeye/internal/cache.py
ribeye/internal/error.py
ribeye/internal/http.py
ribeye/internal/number.py
ribeye/internal/throttle/__init__.py
ribeye/internal/throttle/limiter.py
ribeye/internal/throttle/rate.py
ribeye/internal/throttle/reservation.py
ribeye/internal/time_/__init__.py
ribeye/internal/time_/duration.py
ribeye/internal/time_/types.py
ribeye/internal/types.py
ribeye-0.0.1a1.dist-info/METADATA
ribeye-0.0.1a1.dist-info/WHEEL
ribeye-0.0.1a1.dist-info/RECORD
