Metadata-Version: 2.1
Name: ribeye
Version: 0.0.1a1
Summary: Beef is a Python metaprogramming library for generating HTTP clients using type hints. Beef removes the need for writing boilerplate code for deserialization of Pydantic models, and provides out of the box rate limiting, retries, and caching.
Author: pmateusz
Author-email: pmateusz@users.noreply.github.com
Requires-Python: >=3.9
Classifier: Programming Language :: Python :: 3
Classifier: Programming Language :: Python :: 3.9
Classifier: Programming Language :: Python :: 3.10
Classifier: Programming Language :: Python :: 3.11
Classifier: Programming Language :: Python :: 3.12
Requires-Dist: aiohttp (>=3.7.0)
Requires-Dist: typing-extensions (>=4.7.0)
